tfstage/__init__.py
tfstage/__init__.pyc
tfstage/tfstage.py
tfstage/tfstage.pyc
tfstage/templates/template/.gitignore
tfstage/templates/template/README.md
tfstage/templates/template/requirements.txt
tfstage/templates/template/setup.py
tfstage/templates/template/{{project_name}}/__init__.py
tfstage/templates/template/{{project_name}}/augment.py
tfstage/templates/template/{{project_name}}/experiment.py
tfstage/templates/template/{{project_name}}/inputs.py
tfstage/templates/template/{{project_name}}/main.py
tfstage/templates/template/{{project_name}}/model.py
tfstage/templates/template/{{project_name}}/serve.py
tfstage-0.1.7.data/scripts/tfstage
tfstage-0.1.7.dist-info/DESCRIPTION.rst
tfstage-0.1.7.dist-info/METADATA
tfstage-0.1.7.dist-info/RECORD
tfstage-0.1.7.dist-info/WHEEL
tfstage-0.1.7.dist-info/metadata.json
tfstage-0.1.7.dist-info/top_level.txt
