Metadata-Version: 2.0
Name: tfstage
Version: 0.1.7
Summary: TensorFlow project scaffolding
Home-page: http://github.com/fomorians/tfstage
Author: Jim Fleming
Author-email: jim@fomoro.com
License: MIT
Keywords: tensorflow scaffold scaffolding
Platform: UNKNOWN
Classifier: Development Status :: 2 - Pre-Alpha
Classifier: Intended Audience :: Developers
Classifier: Topic :: Software Development :: Code Generators
Classifier: License :: OSI Approved :: MIT License
Classifier: Programming Language :: Python :: 2.7
Requires-Dist: termcolor
Requires-Dist: pystache
